zalo/__init__.py
zalo/sdk/APIConfig.py
zalo/sdk/APIException.py
zalo/sdk/ZaloBaseClient.py
zalo/sdk/__init__.py
zalo/sdk/app/Zalo3rdAppClient.py
zalo/sdk/app/ZaloAppInfo.py
zalo/sdk/app/__init__.py
zalo/sdk/article/ZaloArticleClient.py
zalo/sdk/article/__init__.py
zalo/sdk/oa/ZaloOaClient.py
zalo/sdk/oa/ZaloOaInfo.py
zalo/sdk/oa/ZaloOaOnbehalf.py
zalo/sdk/oa/__init__.py
zalo/sdk/store/ZaloStoreClient.py
zalo/sdk/store/ZaloStoreOnbehalfClient.py
zalo/sdk/store/__init__.py
zalo/sdk/utils/MacUtils.py
zalo/sdk/utils/__init__.py
zalo_python_sdk-1.17.dist-info/DESCRIPTION.rst
zalo_python_sdk-1.17.dist-info/METADATA
zalo_python_sdk-1.17.dist-info/RECORD
zalo_python_sdk-1.17.dist-info/WHEEL
zalo_python_sdk-1.17.dist-info/metadata.json
zalo_python_sdk-1.17.dist-info/top_level.txt
