Metadata-Version: 2.0
Name: zalo-python-sdk
Version: 1.17
Summary: Python SDK for Zalo API
Home-page: https://github.com/ntkduy123/zalo-python-sdk
Author: Nguyen Thuy Khanh Duy
Author-email: duyntk@vng.com.vn
License: UNKNOWN
Download-URL: https://github.com/ntkduy123/zalo-python-sdk/archive/0.1.tar.gz
Platform: UNKNOWN
